gantt_tasks/__init__.py
gantt_tasks/gantt.py
gantt_tasks/manager.py
gantt_tasks/models.py
gantt_tasks/utils.py
gantt_tasks-0.1.0.dist-info/licenses/license
gantt_tasks-0.1.0.dist-info/METADATA
gantt_tasks-0.1.0.dist-info/WHEEL
gantt_tasks-0.1.0.dist-info/top_level.txt
gantt_tasks-0.1.0.dist-info/RECORD
